ProgramizPythonJiaochengChuyi/README.md
ProgramizPythonJiaochengChuyi/__init__.py
ProgramizPythonJiaochengChuyi/__main__.py
ProgramizPythonJiaochengChuyi/file.epub
ProgramizPythonJiaochengChuyi/index.html
ProgramizPythonJiaochengChuyi/css/__init__.py
ProgramizPythonJiaochengChuyi/css/annotations.css
ProgramizPythonJiaochengChuyi/css/main.css
ProgramizPythonJiaochengChuyi/css/normalize.css
ProgramizPythonJiaochengChuyi/css/popup.css
ProgramizPythonJiaochengChuyi/font/__init__.py
ProgramizPythonJiaochengChuyi/font/fontello.eot
ProgramizPythonJiaochengChuyi/font/fontello.svg
ProgramizPythonJiaochengChuyi/font/fontello.ttf
ProgramizPythonJiaochengChuyi/font/fontello.woff
ProgramizPythonJiaochengChuyi/img/__init__.py
ProgramizPythonJiaochengChuyi/img/annotator-glyph-sprite.png
ProgramizPythonJiaochengChuyi/img/annotator-icon-sprite.png
ProgramizPythonJiaochengChuyi/img/apple-touch-icon.png
ProgramizPythonJiaochengChuyi/img/cancelfullscreen.png
ProgramizPythonJiaochengChuyi/img/close.png
ProgramizPythonJiaochengChuyi/img/fullscreen.png
ProgramizPythonJiaochengChuyi/img/loader.gif
ProgramizPythonJiaochengChuyi/img/menu-icon.png
ProgramizPythonJiaochengChuyi/img/save.png
ProgramizPythonJiaochengChuyi/img/saved.png
ProgramizPythonJiaochengChuyi/img/settings-s.png
ProgramizPythonJiaochengChuyi/img/settings.png
ProgramizPythonJiaochengChuyi/img/star.png
ProgramizPythonJiaochengChuyi/js/__init__.py
ProgramizPythonJiaochengChuyi/js/epub.js
ProgramizPythonJiaochengChuyi/js/epub.min.js
ProgramizPythonJiaochengChuyi/js/epub.min.map
ProgramizPythonJiaochengChuyi/js/hooks.min.js
ProgramizPythonJiaochengChuyi/js/hooks.min.map
ProgramizPythonJiaochengChuyi/js/reader.js
ProgramizPythonJiaochengChuyi/js/reader.js.map
ProgramizPythonJiaochengChuyi/js/reader.min.js
ProgramizPythonJiaochengChuyi/js/reader.min.map
ProgramizPythonJiaochengChuyi/js/hooks/__init__.py
ProgramizPythonJiaochengChuyi/js/hooks/extensions/__init__.py
ProgramizPythonJiaochengChuyi/js/hooks/extensions/highlight.js
programiz_python_jiaocheng_chuyi-2024.3.5.0.dist-info/METADATA
programiz_python_jiaocheng_chuyi-2024.3.5.0.dist-info/WHEEL
programiz_python_jiaocheng_chuyi-2024.3.5.0.dist-info/entry_points.txt
programiz_python_jiaocheng_chuyi-2024.3.5.0.dist-info/top_level.txt
programiz_python_jiaocheng_chuyi-2024.3.5.0.dist-info/RECORD
